{
  "version":"1.0",
  "payload":[
    {
      "INSTANT":{
        "Disk./dev/sda.fs.path":"/",
        "Network.mac_addr":"f2:3c:91:02:54:e7",
        "Disk./dev/sdb.dm":0,
        "Processes.rsyslogd.longname":"/usr/sbin/rsyslogd",
        "Uptime":14450.23,
        "Processes.systemd-journal.longname":"/lib/systemd/systemd-journald",
        "Processes.linode-longview.longname":"linode-longview",
        "Applications.MySQL.status_message":"Unable to connect to the database: Access denied for user 'linode-longview'@'localhost' (using password: YES)",
        "Disk./dev/sda.mounted":1,
        "Ports.active":[
          {
            "count":2,
            "user":"root",
            "name":"sshd"
          },
          {
            "count":8,
            "user":"www-data",
            "name":"apache2"
          }
        ],
        "Disk./dev/sda.isswap":0,
        "Disk./dev/sdb.children":0,
        "Packages":[

        ],
        "SysInfo.cpu.type":"AMD EPYC 7501 32-Core Processor",
        "Disk./dev/sdb.isswap":1,
        "Disk./dev/sda.children":0,
        "Processes.systemd-logind.longname":"/lib/systemd/systemd-logind",
        "Disk./dev/sdb.mounted":0,
        "Ports.listening":[
          {
            "type":"tcp",
            "port":3306,
            "user":"mysql",
            "ip":"127.0.0.1",
            "name":"mysqld"
          },
          {
            "port":22,
            "user":"root",
            "ip":"0.0.0.0",
            "name":"sshd",
            "type":"tcp"
          },
          {
            "type":"tcp6",
            "port":22,
            "ip":"::",
            "user":"root",
            "name":"sshd"
          },
          {
            "type":"tcp6",
            "port":80,
            "name":"apache2",
            "ip":"::",
            "user":"root"
          },
          {
            "name":"apache2",
            "ip":"::",
            "user":"www-data",
            "port":80,
            "type":"tcp6"
          },
          {
            "port":25,
            "ip":"::1",
            "user":"Debian-exim",
            "name":"exim4",
            "type":"tcp6"
          },
          {
            "type":"tcp6",
            "name":"apache2",
            "ip":"::",
            "user":"root",
            "port":443
          },
          {
            "type":"tcp6",
            "name":"apache2",
            "user":"www-data",
            "ip":"::",
            "port":443
          },
          {
            "type":"tcp",
            "name":"exim4",
            "ip":"127.0.0.1",
            "user":"Debian-exim",
            "port":25
          }
        ],
        "Processes.sshd.longname":"/usr/sbin/sshd",
        "SysInfo.os.dist":"Debian",
        "SysInfo.type":"kvm",
        "Processes.exim4.longname":"/usr/sbin/exim4",
        "SysInfo.os.distversion":"10.0",
        "Applications.MySQL.status":2,
        "Processes.htcacheclean.longname":"/usr/bin/htcacheclean",
        "Processes.haveged.longname":"/usr/sbin/haveged",
        "Disk./dev/sda.dm":0,
        "Processes.apache2.longname":"/usr/sbin/apache2",
        "Processes.systemd-timesyn.longname":"/lib/systemd/systemd-timesyncd",
        "SysInfo.client":"1.1.5",
        "Processes.(sd-pam).longname":"(sd-pam)",
        "Processes.systemd.longname":"/lib/systemd/systemd",
        "Processes.dbus-daemon.longname":"/usr/bin/dbus-daemon",
        "Disk./dev/sda.childof":0,
        "SysInfo.cpu.cores":1,
        "SysInfo.hostname":"apache",
        "Processes.agetty.longname":"/sbin/agetty",
        "Processes.systemd-udevd.longname":"/lib/systemd/systemd-udevd",
        "Applications.Apache.version":"Apache/2.4.38 (Debian)",
        "Processes.cron.longname":"/usr/sbin/cron",
        "Processes.bash.longname":"-bash",
        "SysInfo.arch":"x86_64",
        "Applications.Apache.status":0,
        "Processes.mysqld.longname":"/usr/sbin/mysqld",
        "SysInfo.kernel":"Linux 5.1.2-x86_64-linode124",
        "Applications.Apache.status_message":"",
        "Disk./dev/sdb.childof":0
      },
      "timestamp":1560679441,
      "LONGTERM":{
        "Processes.(sd-pam).root.iowritekbytes":0,
        "Processes.systemd-journal.root.mem":14828,
        "Processes.apache2.root.iowritekbytes":0,
        "Applications.Apache.Total Accesses":"13761",
        "Processes.bash.root.cpu":89,
        "Processes.cron.root.iowritekbytes":471040,
        "Memory.swap.used":268,
        "Processes.systemd-journal.root.cpu":924,
        "Processes.systemd-logind.root.ioreadkbytes":237568,
        "Processes.systemd.root.cpu":1185,
        "Processes.bash.root.count":2,
        "Processes.agetty.root.count":2,
        "Applications.Apache.Workers.Closing connection":0,
        "Processes.cron.root.ioreadkbytes":778240,
        "Processes.sshd.root.ioreadkbytes":1429504,
        "Memory.real.cache":543208,
        "Memory.swap.free":524016,
        "Processes.dbus-daemon.messagebus.iowritekbytes":0,
        "CPU.cpu0.user":12043,
        "Processes.mysqld.mysql.iowritekbytes":3092480,
        "Processes.rsyslogd.root.mem":4428,
        "Processes.mysqld.mysql.cpu":403,
        "Applications.Apache.Workers.Sending Reply":1,
        "Processes.(sd-pam).root.ioreadkbytes":0,
        "CPU.cpu0.system":5397,
        "Processes.dbus-daemon.messagebus.count":1,
        "Processes.(sd-pam).root.mem":2756,
        "Processes.cron.root.cpu":2,
        "Processes.apache2.www-data.ioreadkbytes":0,
        "Processes.mysqld.mysql.mem":80812,
        "Processes.mysqld.mysql.ioreadkbytes":4096,
        "Disk./dev/sda.fs.itotal":491520,
        "Applications.Apache.Workers.Keepalive":0,
        "Processes.systemd-journal.root.ioreadkbytes":184320,
        "Load":0,
        "Disk./dev/sda.writes":28243,
        "Processes.dbus-daemon.messagebus.ioreadkbytes":1511424,
        "Processes.apache2.root.ioreadkbytes":0,
        "Processes.apache2.www-data.cpu":3258,
        "Disk./dev/sda.read_bytes":247184384,
        "Network.Interface.eth0.rx_bytes":112048099,
        "Processes.agetty.root.iowritekbytes":4096,
        "Processes.rsyslogd.root.ioreadkbytes":0,
        "Processes.sshd.root.mem":22540,
        "Processes.sshd.root.count":3,
        "Processes.systemd-udevd.root.mem":4468,
        "Network.Interface.lo.rx_bytes":2444095,
        "Processes.haveged.root.count":1,
        "Applications.Apache.Workers.Reading Request":8,
        "Processes.htcacheclean.www-data.ioreadkbytes":0,
        "Processes.rsyslogd.root.count":1,
        "Processes.exim4.Debian-exim.ioreadkbytes":163840,
        "Processes.systemd.root.mem":19392,
        "Disk./dev/sdb.read_bytes":1273856,
        "Processes.htcacheclean.www-data.iowritekbytes":0,
        "Disk./dev/sdb.write_bytes":258048,
        "Processes.haveged.root.ioreadkbytes":0,
        "Processes.systemd-udevd.root.cpu":7,
        "Disk./dev/sdb.writes":36,
        "Processes.agetty.root.ioreadkbytes":139264,
        "Applications.Apache.Total kBytes":"189222",
        "Processes.systemd-journal.root.count":1,
        "Processes.bash.root.mem":11972,
        "Network.Interface.eth0.tx_bytes":263396409,
        "Processes.systemd-logind.root.mem":7132,
        "Disk./dev/sda.fs.free":6981713920,
        "Processes.systemd.root.iowritekbytes":216387584,
        "Processes.dbus-daemon.messagebus.mem":4168,
        "Processes.apache2.www-data.iowritekbytes":2535424,
        "Processes.agetty.root.mem":3512,
        "Processes.exim4.Debian-exim.mem":4444,
        "Applications.Apache.Workers.Idle cleanup of worker":0,
        "Processes.haveged.root.iowritekbytes":0,
        "Processes.systemd-udevd.root.iowritekbytes":0,
        "Processes.(sd-pam).root.count":1,
        "Processes.bash.root.ioreadkbytes":94998528,
        "Processes.htcacheclean.www-data.mem":184,
        "Processes.apache2.root.cpu":37,
        "Disk./dev/sda.fs.ifree":453861,
        "Processes.agetty.root.cpu":7,
        "Processes.systemd.root.count":2,
        "Disk./dev/sda.write_bytes":1619398656,
        "Processes.apache2.www-data.mem":41920,
        "Processes.exim4.Debian-exim.count":1,
        "Applications.Apache.Workers.Gracefully finishing":0,
        "Processes.systemd-timesyn.systemd-timesync.iowritekbytes":0,
        "Processes.systemd-logind.root.iowritekbytes":0,
        "Processes.cron.root.count":1,
        "Processes.systemd-udevd.root.ioreadkbytes":7335936,
        "Processes.systemd.root.ioreadkbytes":141388800,
        "Disk./dev/sda.fs.total":8429953024,
        "Processes.cron.root.mem":2772,
        "Applications.Apache.Workers.Starting up":0,
        "Processes.(sd-pam).root.cpu":0,
        "Processes.apache2.www-data.count":3,
        "Applications.Apache.Workers.Waiting for Connection":66,
        "Processes.rsyslogd.root.cpu":570,
        "Processes.apache2.root.mem":7412,
        "Memory.real.free":131756,
        "Memory.real.buffers":39372,
        "Disk./dev/sda.reads":7540,
        "Processes.htcacheclean.www-data.cpu":19,
        "Processes.htcacheclean.www-data.count":1,
        "Processes.rsyslogd.root.iowritekbytes":42770432,
        "Processes.systemd-timesyn.systemd-timesync.ioreadkbytes":335872,
        "Processes.systemd-logind.root.count":1,
        "Processes.sshd.root.cpu":352,
        "Memory.real.used":859896,
        "Processes.apache2.root.count":1,
        "Processes.systemd-journal.root.iowritekbytes":0,
        "Processes.systemd-udevd.root.count":1,
        "Applications.Apache.Workers.DNS Lookup":0,
        "Network.Interface.lo.tx_bytes":2444095,
        "Processes.systemd-timesyn.systemd-timesync.cpu":5,
        "Processes.bash.root.iowritekbytes":637911040,
        "Processes.exim4.Debian-exim.cpu":0,
        "Disk./dev/sdb.reads":56,
        "Processes.sshd.root.iowritekbytes":601563136,
        "Processes.exim4.Debian-exim.iowritekbytes":36864,
        "Processes.systemd-timesyn.systemd-timesync.count":1,
        "Processes.haveged.root.mem":4752,
        "Processes.haveged.root.cpu":30,
        "CPU.cpu0.wait":443,
        "Processes.mysqld.mysql.count":1,
        "Processes.systemd-logind.root.cpu":75,
        "Applications.Apache.Workers.Logging":0,
        "Processes.systemd-timesyn.systemd-timesync.mem":6400,
        "Processes.dbus-daemon.messagebus.cpu":202
      }
    }
  ],
  "timestamp":1560679443,
  "apikey":"B6EEAB78-DAC1-12BB-55A06A8AD70521FF"
}
